msmbuilder2022.libs/libgomp-9aeda304.so.1.0.0
msmbuilder/libdistance.cpython-39-x86_64-linux-gnu.so
msmbuilder/version.py
msmbuilder/cmdline.py
msmbuilder/base.py
msmbuilder/dataset.py
msmbuilder/__init__.py
msmbuilder/preprocessing/timeseries.py
msmbuilder/preprocessing/base.py
msmbuilder/preprocessing/__init__.py
msmbuilder/feature_extraction/__init__.py
msmbuilder/project_templates/1-get-example-data.py
msmbuilder/project_templates/README.md
msmbuilder/project_templates/plot_macros.template
msmbuilder/project_templates/0-test-install.py
msmbuilder/project_templates/plot_header.template
msmbuilder/project_templates/LICENSE.md
msmbuilder/project_templates/landmarks/featurize-plot.py
msmbuilder/project_templates/landmarks/featurize.py
msmbuilder/project_templates/landmarks/find-landmarks.py
msmbuilder/project_templates/cluster/cluster-plot.py
msmbuilder/project_templates/cluster/cluster.py
msmbuilder/project_templates/cluster/sample-clusters.py
msmbuilder/project_templates/cluster/sample-clusters-plot.py
msmbuilder/project_templates/dihedrals/featurize-plot.py
msmbuilder/project_templates/dihedrals/featurize.py
msmbuilder/project_templates/tica/tica-sample-coordinate-plot.py
msmbuilder/project_templates/tica/tica-sample-coordinate.py
msmbuilder/project_templates/tica/tica-plot.py
msmbuilder/project_templates/tica/tica.py
msmbuilder/project_templates/analysis/gather-metadata-plot.py
msmbuilder/project_templates/analysis/gather-metadata.py
msmbuilder/project_templates/rmsd/rmsd-plot.py
msmbuilder/project_templates/rmsd/rmsd.py
msmbuilder/project_templates/msm/microstate.py
msmbuilder/project_templates/msm/microstate-traj.py
msmbuilder/project_templates/msm/timescales-plot.py
msmbuilder/project_templates/msm/microstate-plot.py
msmbuilder/project_templates/msm/timescales.py
msmbuilder/tests/test_ratematrix.py
msmbuilder/tests/test_dataset.py
msmbuilder/tests/test_bootstrap_msm.py
msmbuilder/tests/test_nearest.py
msmbuilder2022-3.8.6.dist-info/METADATA
msmbuilder2022-3.8.6.dist-info/WHEEL
msmbuilder2022-3.8.6.dist-info/top_level.txt
msmbuilder2022-3.8.6.dist-info/LICENSE
msmbuilder2022-3.8.6.dist-info/entry_points.txt
msmbuilder2022-3.8.6.dist-info/RECORD
