Metadata-Version: 2.1
Name: msmbuilder2022
Version: 3.8.6
Summary: MSMBuilder: Statistical models for Biomolecular Dynamics
Home-page: https://github.com/msmbuilder/msmbuilder
Author: Robert McGibbon
Author-email: rmcgibbo@gmail.com
Platform: Linux
Platform: Mac OS-X
Platform: Unix
Classifier: Intended Audience :: Science/Research
Classifier: Intended Audience :: Developers
Classifier: License :: OSI Approved :: GNU Lesser General Public License v2 or later (LGPLv2+)
Classifier: Programming Language :: C++
Classifier: Programming Language :: Python
Classifier: Development Status :: 5 - Production/Stable
Classifier: Topic :: Software Development
Classifier: Topic :: Scientific/Engineering
Classifier: Operating System :: POSIX
Classifier: Operating System :: Unix
Classifier: Operating System :: MacOS
Classifier: Programming Language :: Python :: 3.7
Classifier: Programming Language :: Python :: 3.8
Classifier: Programming Language :: Python :: 3.9
License-File: LICENSE
Requires-Dist: numpy
Requires-Dist: mdtraj-duplicate
Requires-Dist: scikit-learn
Requires-Dist: pandas
Requires-Dist: fastcluster
Requires-Dist: jinja2
Requires-Dist: pyyaml
Requires-Dist: tables
Requires-Dist: numpydoc
Requires-Dist: six
Requires-Dist: scipy
Requires-Dist: pyhmc-duplicate
